arbiter/__init__.py
arbiter/cli.py
arbiter/config.py
arbiter/costs.py
arbiter/evaluator.py
arbiter/judge.py
arbiter/utils.py
arbiter/assets/__init__.py
arbiter/assets/example_evals.json
arbiter/assets/favicon.ico
arbiter/assets/index.html
arbiter/commands/__init__.py
arbiter/commands/common.py
arbiter/commands/council.py
arbiter/commands/execute.py
arbiter/commands/forge.py
arbiter/commands/genesis.py
arbiter_mcp_evals-0.1.0.dist-info/licenses/LICENSE
arbiter_mcp_evals-0.1.0.dist-info/METADATA
arbiter_mcp_evals-0.1.0.dist-info/WHEEL
arbiter_mcp_evals-0.1.0.dist-info/entry_points.txt
arbiter_mcp_evals-0.1.0.dist-info/top_level.txt
arbiter_mcp_evals-0.1.0.dist-info/RECORD
