Metadata-Version: 2.4
Name: arbiter-mcp-evals
Version: 0.1.0
Summary: Lightweight framework for generating, running, and reviewing MCP evals.
Author-email: Alexander Galea <alex@galea.dev>
License: MIT
Project-URL: Homepage, https://pypi.org/project/arbiter-mcp-evals/
Project-URL: Repository, https://github.com/zazencodes/arbiter-mcp-evals
Project-URL: Changelog, https://github.com/zazencodes/arbiter-mcp-evals/blob/main/CHANGELOG.md
Project-URL: Issues, https://github.com/zazencodes/arbiter-mcp-evals/issues
Keywords: arbiter,llm,evaluation,mcp,testing
Classifier: Programming Language :: Python :: 3
Classifier: Programming Language :: Python :: 3 :: Only
Classifier: Programming Language :: Python :: 3.12
Classifier: Programming Language :: Python :: 3.13
Classifier: License :: OSI Approved :: MIT License
Classifier: Operating System :: OS Independent
Classifier: Typing :: Typed
Requires-Python: >=3.12
License-File: LICENSE
Requires-Dist: langchain<1.0.0,>=0.3.27
Requires-Dist: langgraph<1.0.0,>=0.6.7
Requires-Dist: langchain-anthropic<1.0.0,>=0.3.20
Requires-Dist: langchain-openai<1.0.0,>=0.3.33
Requires-Dist: langchain-google-genai<3.0.0,>=2.1.12
Requires-Dist: langchain-mcp-adapters<1.0.0,>=0.1.10
Requires-Dist: pydantic<3.0.0,>=2.11.9
Requires-Dist: rich<15.0.0,>=14.1.0
Requires-Dist: litellm<2.0.0,>=1.77.1
Requires-Dist: fastapi<1.0.0,>=0.112.0
Requires-Dist: uvicorn<1.0.0,>=0.30.0
Provides-Extra: dev
Requires-Dist: pytest<9.0.0,>=8.4.2; extra == "dev"
Requires-Dist: pytest-asyncio<2.0.0,>=1.2.0; extra == "dev"
Requires-Dist: pytest-cov<8.0.0,>=7.0.0; extra == "dev"
Requires-Dist: ruff<1.0.0,>=0.13.1; extra == "dev"
Requires-Dist: mypy<2.0.0,>=1.18.2; extra == "dev"
Requires-Dist: isort<6.0.0,>=5.13.2; extra == "dev"
Dynamic: license-file
